{"version": "https://jsonfeed.org/version/1", "title": "HackOps Notes", "home_page_url": "https://tonuser.github.io/hackops/", "feed_url": "https://tonuser.github.io/hackops/feed_json_created.json", "description": "Cheatsheets & notes de s\u00e9cu fa\u00e7on HackTricks", "icon": null, "authors": [{"name": "Ton Nom"}], "language": "fr", "items": [{"id": "https://tonuser.github.io/hackops/", "url": "https://tonuser.github.io/hackops/", "title": "Home", "content_html": "", "image": null, "date_published": "2025-09-08T19:31:14+00:00", "authors": [], "tags": null}]}